[
    {
        "name": "Permissão",
        "namecomplete": "Plataforma - Permissão",
        "js": null,
        "wherefixed": null,
        "orderfixed": null,
        "supressid": false,
        "template": "box-6",
        "model": "permission",
        "module": "Plataforma",
        "_field": [
            {
                "templatezone": "z1",
                "modelattribute": "insertable",
                "width": 3,
                "order": 4,
                "disabled": false,
                "disablefilter": false
            },
            {
                "templatezone": "z1",
                "modelattribute": "editable",
                "width": 3,
                "order": 5,
                "disabled": false,
                "disablefilter": false
            },
            {
                "templatezone": "z1",
                "modelattribute": "deletable",
                "width": 3,
                "order": 6,
                "disabled": false,
                "disablefilter": false
            },
            {
                "templatezone": "z1",
                "modelattribute": "visible",
                "width": 3,
                "order": 3,
                "disabled": false,
                "disablefilter": false
            },
            {
                "templatezone": "z1",
                "modelattribute": "iduser",
                "width": 12,
                "order": 1,
                "disabled": false,
                "disablefilter": false
            },
            {
                "templatezone": "z1",
                "modelattribute": "idmenu",
                "width": 12,
                "order": 2,
                "disabled": false,
                "disablefilter": false
            }
        ],
        "_table": [
            {
                "modelattribute": "insertable",
                "ordertable": 4,
                "orderable": true,
                "render": "boolean",
                "totalize": null,
                "class": null
            },
            {
                "modelattribute": "editable",
                "ordertable": 5,
                "orderable": true,
                "render": "boolean",
                "totalize": null,
                "class": null
            },
            {
                "modelattribute": "deletable",
                "ordertable": 6,
                "orderable": true,
                "render": "boolean",
                "totalize": null,
                "class": null
            },
            {
                "modelattribute": "visible",
                "ordertable": 3,
                "orderable": true,
                "render": "boolean",
                "totalize": null,
                "class": null
            },
            {
                "modelattribute": "iduser",
                "ordertable": 1,
                "orderable": true,
                "render": null,
                "totalize": null,
                "class": null
            },
            {
                "modelattribute": "idmenu",
                "ordertable": 2,
                "orderable": true,
                "render": null,
                "totalize": null,
                "class": null
            }
        ],
        "_subview": [],
        "_event": []
    }
]